tinyscaler.cp312-win_amd64.pyd
tinyscaler-1.2.8.dist-info/LICENSE
tinyscaler-1.2.8.dist-info/METADATA
tinyscaler-1.2.8.dist-info/WHEEL
tinyscaler-1.2.8.dist-info/top_level.txt
tinyscaler-1.2.8.dist-info/RECORD
