Metadata-Version: 2.1
Name: tinyscaler
Version: 1.2.8
Summary: A tiny, simple image scaler.
Author-email: Farama Foundation <contact@farama.org>
License: MIT License
Project-URL: Homepage, https://farama.org
Project-URL: Repository, https://github.com/Farama-Foundation/TinyScaler
Project-URL: Documentation, https://github.com/Farama-Foundation/TinyScaler
Project-URL: Bug Report, https://github.com/Farama-Foundation/TinyScaler/issues
Keywords: Reinforcement Learning,Gymnasium,PettingZoo
Classifier: Development Status :: 4 - Beta
Classifier: License :: OSI Approved :: MIT License
Classifier: Programming Language :: Python :: 3
Classifier: Programming Language :: Python :: 3.8
Classifier: Programming Language :: Python :: 3.9
Classifier: Programming Language :: Python :: 3.10
Classifier: Programming Language :: Python :: 3.11
Classifier: Programming Language :: Python :: 3.12
Classifier: Intended Audience :: Science/Research
Classifier: Topic :: Scientific/Engineering :: Artificial Intelligence
Requires-Python: >=3.8
License-File: LICENSE
Requires-Dist: numpy>=1.21.0
